LICENSE
MANIFEST.in
README.md
setup.py
django_eveonline_timerboard/__init__.py
django_eveonline_timerboard/admin.py
django_eveonline_timerboard/apps.py
django_eveonline_timerboard/bindings.py
django_eveonline_timerboard/forms.py
django_eveonline_timerboard/models.py
django_eveonline_timerboard/tests.py
django_eveonline_timerboard/urls.py
django_eveonline_timerboard/views.py
django_eveonline_timerboard.egg-info/PKG-INFO
django_eveonline_timerboard.egg-info/SOURCES.txt
django_eveonline_timerboard.egg-info/dependency_links.txt
django_eveonline_timerboard.egg-info/requires.txt
django_eveonline_timerboard.egg-info/top_level.txt
django_eveonline_timerboard/migrations/0001_initial.py
django_eveonline_timerboard/migrations/0002_auto_20190917_2024.py
django_eveonline_timerboard/migrations/0003_populate_default_types.py
django_eveonline_timerboard/migrations/__init__.py
django_eveonline_timerboard/templates/django_eveonline_timerboard/sidebar.html
django_eveonline_timerboard/templates/django_eveonline_timerboard/adminlte/timerboard.html
django_eveonline_timerboard/templates/django_eveonline_timerboard/adminlte/components/timer_button.html
django_eveonline_timerboard/templates/django_eveonline_timerboard/adminlte/components/timer_modal.html