Metadata-Version: 2.1
Name: django-eveonline-timerboard
Version: 1.1.0
Summary: A simple timerboard extension with EVE Online flavor
Home-page: https://github.com/KryptedGaming/django-eveonline-timerboard
Author: porowns
Author-email: porowns@gmail.com
License: MIT License
Platform: UNKNOWN
Classifier: Environment :: Web Environment
Classifier: Framework :: Django
Classifier: Intended Audience :: Developers
Classifier: License :: OSI Approved :: MIT License
Classifier: Operating System :: OS Independent
Classifier: Programming Language :: Python
Classifier: Programming Language :: Python :: 3.5
Classifier: Programming Language :: Python :: 3.6
Classifier: Topic :: Internet :: WWW/HTTP
Classifier: Topic :: Internet :: WWW/HTTP :: Dynamic Content
